tests/__init__.py
tests/conftest.py
tests/test_cookiecutter_generation.py
cookiecutter_toil-2.0.0.dist-info/LICENSE
cookiecutter_toil-2.0.0.dist-info/METADATA
cookiecutter_toil-2.0.0.dist-info/WHEEL
cookiecutter_toil-2.0.0.dist-info/top_level.txt
cookiecutter_toil-2.0.0.dist-info/RECORD
